lewaf/.DS_Store
lewaf/__init__.py
lewaf/bodyprocessors/__init__.py
lewaf/bodyprocessors/base.py
lewaf/bodyprocessors/json.py
lewaf/bodyprocessors/multipart.py
lewaf/bodyprocessors/protocol.py
lewaf/bodyprocessors/registry.py
lewaf/bodyprocessors/urlencoded.py
lewaf/bodyprocessors/xml.py
lewaf/cli/__init__.py
lewaf/cli/validate.py
lewaf/config/__init__.py
lewaf/config/loader.py
lewaf/config/manager.py
lewaf/config/models.py
lewaf/config/profiles.py
lewaf/config/validator.py
lewaf/core/__init__.py
lewaf/engine/__init__.py
lewaf/exceptions.py
lewaf/integration/__init__.py
lewaf/integration/asgi.py
lewaf/integrations/__init__.py
lewaf/integrations/django.py
lewaf/integrations/flask.py
lewaf/integrations/starlette.py
lewaf/kernel/__init__.py
lewaf/kernel/protocol.py
lewaf/kernel/python_kernel.py
lewaf/logging/__init__.py
lewaf/logging/audit.py
lewaf/logging/error_logger.py
lewaf/logging/formatters.py
lewaf/logging/masking.py
lewaf/primitives/__init__.py
lewaf/primitives/actions/__init__.py
lewaf/primitives/actions/_base.py
lewaf/primitives/actions/blocking.py
lewaf/primitives/actions/collections.py
lewaf/primitives/actions/flow_control.py
lewaf/primitives/actions/logging_actions.py
lewaf/primitives/actions/metadata.py
lewaf/primitives/actions/transformation.py
lewaf/primitives/actions/variables.py
lewaf/primitives/collections.py
lewaf/primitives/operators/__init__.py
lewaf/primitives/operators/_base.py
lewaf/primitives/operators/comparison.py
lewaf/primitives/operators/control.py
lewaf/primitives/operators/detection.py
lewaf/primitives/operators/inspection.py
lewaf/primitives/operators/matching.py
lewaf/primitives/operators/network.py
lewaf/primitives/operators/validation.py
lewaf/primitives/transformations.py
lewaf/primitives/variable_expansion.py
lewaf/proxy/__init__.py
lewaf/proxy/cli.py
lewaf/proxy/client.py
lewaf/proxy/server.py
lewaf/rules/__init__.py
lewaf/seclang/__init__.py
lewaf/seclang/parser.py
lewaf/seclang/rule_parser.py
lewaf/storage/__init__.py
lewaf-0.7.2.dist-info/WHEEL
lewaf-0.7.2.dist-info/entry_points.txt
lewaf-0.7.2.dist-info/METADATA
lewaf-0.7.2.dist-info/RECORD
