Metadata-Version: 2.3
Name: lewaf
Version: 0.7.2
Summary: A Web Application Firewall for Python that stops attacks before they reach your application code, with comprehensive audit logging and compliance support.
Keywords: waf,security,modsecurity,firewall,web-security,owasp
Author: Stefane Fermigier
Author-email: Stefane Fermigier <sf@abilian.com>
License: Apache-2.0
Classifier: Development Status :: 4 - Beta
Classifier: Intended Audience :: Developers
Classifier: License :: OSI Approved :: Apache Software License
Classifier: Programming Language :: Python :: 3
Classifier: Programming Language :: Python :: 3.12
Classifier: Topic :: Security
Classifier: Topic :: Internet :: WWW/HTTP :: WSGI :: Middleware
Requires-Dist: starlette>=0.41.0
Requires-Dist: httpx>=0.27.0
Requires-Dist: uvicorn>=0.32.0
Requires-Dist: redis>=7.0.1
Requires-Dist: pyyaml>=6.0.3
Requires-Dist: click>=8.2.1
Requires-Python: >=3.12
Project-URL: Documentation, https://github.com/abilian/lewaf/tree/main/docs
Project-URL: Homepage, https://github.com/abilian/lewaf
Project-URL: Issues, https://github.com/abilian/lewaf/issues
Project-URL: Repository, https://github.com/abilian/lewaf
